scripts/__init__.py
scripts/create_basic_auth_user.py
scripts/install.sh
shraga_common/Dockerfile
shraga_common/__init__.py
shraga_common/app/__init__.py
shraga_common/app/auth/__init__.py
shraga_common/app/auth/basic_auth.py
shraga_common/app/auth/google_auth.py
shraga_common/app/auth/jwt_auth.py
shraga_common/app/auth/microsoft_auth.py
shraga_common/app/auth/test_basic_auth.py
shraga_common/app/auth/test_jwt_auth.py
shraga_common/app/auth/test_jwt_auth_extended.py
shraga_common/app/auth/user.py
shraga_common/app/config/__init__.py
shraga_common/app/middlewares.py
shraga_common/app/models/__init__.py
shraga_common/app/models/analytics_request.py
shraga_common/app/models/api_requests.py
shraga_common/app/models/chat.py
shraga_common/app/models/feedback_request.py
shraga_common/app/models/report_request.py
shraga_common/app/routers/__init__.py
shraga_common/app/routers/analytics_api.py
shraga_common/app/routers/api_app.py
shraga_common/app/routers/flows_api.py
shraga_common/app/routers/history_api.py
shraga_common/app/routers/oauth_app.py
shraga_common/app/routers/report_api.py
shraga_common/app/routers/request_utils.py
shraga_common/app/routers/run_flow.py
shraga_common/app/routers/secrets_api.py
shraga_common/app/routers/services_api.py
shraga_common/app/routers/setup.py
shraga_common/app/services/__init__.py
shraga_common/app/services/analytics_service.py
shraga_common/app/services/get_history_client.py
shraga_common/app/services/history_service.py
shraga_common/app/services/list_flows_service.py
shraga_common/app/services/report_service.py
shraga_common/app/services/test_log_interaction.py
shraga_common/app/utils.py
shraga_common/embedders/__init__.py
shraga_common/embedders/base_embedder.py
shraga_common/embedders/bedrock_embedder.py
shraga_common/embedders/cohere_embedder.py
shraga_common/embedders/google_embedder.py
shraga_common/embedders/openai_embedder.py
shraga_common/embedders/snowflake_huggingface_embedder.py
shraga_common-0.8.7.dist-info/LICENSE
shraga_common-0.8.7.dist-info/METADATA
shraga_common-0.8.7.dist-info/WHEEL
shraga_common-0.8.7.dist-info/entry_points.txt
shraga_common-0.8.7.dist-info/RECORD
